<?xml version="1.0" encoding="UTF-8"?>
<GenRun Id="synth_1" LaunchPart="xc7a200tfbg676-2" LaunchTime="1576834592">
  <File Type="PA-TCL" Name="keccak.tcl"/>
  <File Type="REPORTS-TCL" Name="keccak_reports.tcl"/>
  <File Type="RDS-RDS" Name="keccak.vds"/>
  <File Type="RDS-UTIL" Name="keccak_utilization_synth.rpt"/>
  <File Type="RDS-UTIL-PB" Name="keccak_utilization_synth.pb"/>
  <File Type="RDS-DCP" Name="keccak.dcp"/>
  <FileSet Name="sources" Type="DesignSrcs" RelSrcDir="$PSRCDIR/sources_1">
    <Filter Type="Srcs"/>
    <File Path="$PSRCDIR/sources_1/imports/rtl/f_permutation.v">
      <FileInfo>
        <Attr Name="ImportPath" Val="$PPRDIR/../../../../Desktop/sha3_latest/sha3/trunk/low_throughput_core/rtl/f_permutation.v"/>
        <Attr Name="ImportTime" Val="1359097870"/>
        <Attr Name="UsedIn" Val="synthesis"/>
        <Attr Name="UsedIn" Val="implementation"/>
        <Attr Name="UsedIn" Val="simulation"/>
      </FileInfo>
    </File>
    <File Path="$PSRCDIR/sources_1/imports/rtl/padder.v">
      <FileInfo>
        <Attr Name="ImportPath" Val="$PPRDIR/../../../../Desktop/sha3_latest/sha3/trunk/low_throughput_core/rtl/padder.v"/>
        <Attr Name="ImportTime" Val="1359097870"/>
        <Attr Name="UsedIn" Val="synthesis"/>
        <Attr Name="UsedIn" Val="implementation"/>
        <Attr Name="UsedIn" Val="simulation"/>
      </FileInfo>
    </File>
    <File Path="$PSRCDIR/sources_1/imports/rtl/padder1.v">
      <FileInfo>
        <Attr Name="ImportPath" Val="$PPRDIR/../../../../Desktop/sha3_latest/sha3/trunk/low_throughput_core/rtl/padder1.v"/>
        <Attr Name="ImportTime" Val="1359097870"/>
        <Attr Name="UsedIn" Val="synthesis"/>
        <Attr Name="UsedIn" Val="implementation"/>
        <Attr Name="UsedIn" Val="simulation"/>
      </FileInfo>
    </File>
    <File Path="$PSRCDIR/sources_1/imports/rtl/rconst.v">
      <FileInfo>
        <Attr Name="ImportPath" Val="$PPRDIR/../../../../Desktop/sha3_latest/sha3/trunk/low_throughput_core/rtl/rconst.v"/>
        <Attr Name="ImportTime" Val="1359097870"/>
        <Attr Name="UsedIn" Val="synthesis"/>
        <Attr Name="UsedIn" Val="implementation"/>
        <Attr Name="UsedIn" Val="simulation"/>
      </FileInfo>
    </File>
    <File Path="$PSRCDIR/sources_1/imports/rtl/round.v">
      <FileInfo>
        <Attr Name="ImportPath" Val="$PPRDIR/../../../../Desktop/sha3_latest/sha3/trunk/low_throughput_core/rtl/round.v"/>
        <Attr Name="ImportTime" Val="1359097870"/>
        <Attr Name="UsedIn" Val="synthesis"/>
        <Attr Name="UsedIn" Val="implementation"/>
        <Attr Name="UsedIn" Val="simulation"/>
      </FileInfo>
    </File>
    <File Path="$PSRCDIR/sources_1/imports/rtl/keccak.v">
      <FileInfo>
        <Attr Name="ImportPath" Val="$PPRDIR/../../../../Desktop/sha3_latest/sha3/trunk/low_throughput_core/rtl/keccak.v"/>
        <Attr Name="ImportTime" Val="1359097870"/>
        <Attr Name="UsedIn" Val="synthesis"/>
        <Attr Name="UsedIn" Val="implementation"/>
        <Attr Name="UsedIn" Val="simulation"/>
      </FileInfo>
    </File>
    <Config>
      <Option Name="DesignMode" Val="RTL"/>
      <Option Name="TopModule" Val="keccak"/>
      <Option Name="TopAutoSet" Val="TRUE"/>
    </Config>
  </FileSet>
  <FileSet Name="constrs_in" Type="Constrs" RelSrcDir="$PSRCDIR/constrs_1">
    <Filter Type="Constrs"/>
    <File Path="$PSRCDIR/constrs_1/new/usr_constrain.xdc">
      <FileInfo>
        <Attr Name="UsedIn" Val="synthesis"/>
        <Attr Name="UsedIn" Val="implementation"/>
      </FileInfo>
    </File>
    <Config>
      <Option Name="TargetConstrsFile" Val="$PSRCDIR/constrs_1/new/usr_constrain.xdc"/>
      <Option Name="ConstrsType" Val="XDC"/>
    </Config>
  </FileSet>
  <Strategy Version="1" Minor="2">
    <StratHandle Name="Vivado Synthesis Defaults" Flow="Vivado Synthesis 2018"/>
    <Step Id="synth_design"/>
  </Strategy>
</GenRun>
